findbugs2junit/findbugs2junit.py
findbugs2junit-2018.3.23.41338.dist-info/DESCRIPTION.rst
findbugs2junit-2018.3.23.41338.dist-info/METADATA
findbugs2junit-2018.3.23.41338.dist-info/RECORD
findbugs2junit-2018.3.23.41338.dist-info/WHEEL
findbugs2junit-2018.3.23.41338.dist-info/entry_points.txt
findbugs2junit-2018.3.23.41338.dist-info/metadata.json
findbugs2junit-2018.3.23.41338.dist-info/top_level.txt
