Metadata-Version: 2.0
Name: findbugs2junit
Version: 2018.3.23.41338
Summary: Convert findbugs xml report to junit report
Home-page: https://github.com/hughsaunders/findbugs2junit
Author: Hugh Saunders
Author-email: hugh@wherenow.org
License: Apache
Platform: UNKNOWN
Requires-Python: >=3
Requires-Dist: click (==6.7)
Requires-Dist: junit-xml (==1.8)
